ansible_analyzer/__init__.py
ansible_analyzer/graph.py
ansible_analyzer/log.py
ansible_analyzer/main.py
ansible_analyzer-0.1.1.dist-info/WHEEL
ansible_analyzer-0.1.1.dist-info/entry_points.txt
ansible_analyzer-0.1.1.dist-info/METADATA
ansible_analyzer-0.1.1.dist-info/RECORD
