Metadata-Version: 2.3
Name: ansible-analyzer
Version: 0.1.1
Summary: CLI for Ansible role & playbook analysis & visualization
Author: Valentine Shatravenko
Author-email: Valentine Shatravenko <vshatravenko@gmail.com>
Requires-Dist: pydot>=4.0.1
Requires-Dist: pyyaml>=6.0.3
Requires-Python: >=3.10
